LICENSE
MANIFEST.in
README.rst
setup.cfg
setup.py
docs/Makefile
docs/source/CHANGELOG.rst
docs/source/README.rst
docs/source/conf.py
docs/source/index.rst
docs/source/modules/index.rst
j2skaffold/__init__.py
j2skaffold/cli.py
j2skaffold/templating.py
j2skaffold.egg-info/PKG-INFO
j2skaffold.egg-info/SOURCES.txt
j2skaffold.egg-info/dependency_links.txt
j2skaffold.egg-info/entry_points.txt
j2skaffold.egg-info/requires.txt
j2skaffold.egg-info/top_level.txt
j2skaffold/tests/__init__.py
j2skaffold/tests/test_templating.py